velatus-0.3.0.dist-info/METADATA
velatus-0.3.0.dist-info/WHEEL
velatus-0.3.0.dist-info/licenses/LICENSE
velatus/py.typed
velatus/velatus.pyi
velatus/__init__.py
velatus/velatus.cpython-38-aarch64-linux-gnu.so
velatus-0.3.0.dist-info/RECORD
