Metadata-Version: 2.4
Name: velatus
Version: 0.3.0
Classifier: Programming Language :: Rust
Classifier: Programming Language :: Python :: Implementation :: CPython
Classifier: Programming Language :: Python :: Implementation :: PyPy
Requires-Dist: pytest>=8 ; extra == 'tests'
Requires-Dist: pytest-benchmark>=5 ; extra == 'tests'
Requires-Dist: mypy>=1.15.0 ; extra == 'tests'
Provides-Extra: tests
License-File: LICENSE
Summary: A Python library for masking sensitive information in logs.
Author-email: Max Dymond <cmeister2@gmail.com>
Requires-Python: >=3.8
